dexscreen/__init__.py
dexscreen/api/__init__.py
dexscreen/api/client.py
dexscreen/config/__init__.py
dexscreen/core/__init__.py
dexscreen/core/exceptions.py
dexscreen/core/http.py
dexscreen/core/models.py
dexscreen/core/validators.py
dexscreen/stream/__init__.py
dexscreen/stream/polling.py
dexscreen/utils/__init__.py
dexscreen/utils/browser_selector.py
dexscreen/utils/filters.py
dexscreen/utils/logging_config.py
dexscreen/utils/middleware.py
dexscreen/utils/ratelimit.py
dexscreen/utils/retry.py
dexscreen-0.0.7.dist-info/METADATA
dexscreen-0.0.7.dist-info/WHEEL
dexscreen-0.0.7.dist-info/licenses/LICENSE
dexscreen-0.0.7.dist-info/RECORD
