Metadata-Version: 2.4
Name: dexscreen
Version: 0.0.7
Summary: Python wrapper for Dexscreener API with stable HTTP support
Project-URL: Repository, https://github.com/solanab/dexscreen
Project-URL: Documentation, https://github.com/solanab/dexscreen#readme
Project-URL: Issues, https://github.com/solanab/dexscreen/issues
Author-email: solanab <whiredj@gmail.com>
License: MIT
License-File: LICENSE
Keywords: api,crypto,cryptocurrency,dexscreener,http
Classifier: Development Status :: 4 - Beta
Classifier: Intended Audience :: Developers
Classifier: License :: OSI Approved :: MIT License
Classifier: Operating System :: OS Independent
Classifier: Programming Language :: Python :: 3
Classifier: Programming Language :: Python :: 3.9
Classifier: Programming Language :: Python :: 3.10
Classifier: Programming Language :: Python :: 3.11
Classifier: Programming Language :: Python :: 3.12
Classifier: Programming Language :: Python :: 3.13
Classifier: Topic :: Software Development :: Libraries :: Python Modules
Requires-Python: >=3.9
Requires-Dist: curl-cffi>=0.12
Requires-Dist: orjson>=3.11
Requires-Dist: pydantic>=2.11
